LICENSE
MANIFEST.in
README.rst
setup.py
materialize_tornado_quickstart.egg-info/PKG-INFO
materialize_tornado_quickstart.egg-info/SOURCES.txt
materialize_tornado_quickstart.egg-info/dependency_links.txt
materialize_tornado_quickstart.egg-info/entry_points.txt
materialize_tornado_quickstart.egg-info/not-zip-safe
materialize_tornado_quickstart.egg-info/requires.txt
materialize_tornado_quickstart.egg-info/top_level.txt
mywebapp/__init__.py
mywebapp/webapp.py
mywebapp/website.py
tests/__init__.py
tests/test_webapp.py