Metadata-Version: 1.1
Name: materialize-tornado-quickstart
Version: 1.0.0
Summary: A quickstart template for a materializecss tornado webapp
Home-page: https://github.com/johnl/materialize-tornado-quickstart
Author: John Lehmann
Author-email: j1o1h1n@yahoo.com
License: MIT License
Platform: UNKNOWN
Classifier: Programming Language :: Python
